illuminatus/__init__.py
illuminatus/base.py
illuminatus/db.py
illuminatus/export.py
illuminatus/photos.py
illuminatus/util.py
illuminatus/videos.py
illuminatus/commands/__init__.py
illuminatus/commands/export.py
illuminatus/commands/import_.py
illuminatus/commands/ls.py
illuminatus/commands/retag.py
illuminatus/commands/rethumb.py
illuminatus/commands/serve.py
illuminatus/commands/wedding.py
illuminatus-0.0.1.data/scripts/illuminatus
illuminatus-0.0.1.dist-info/DESCRIPTION.rst
illuminatus-0.0.1.dist-info/METADATA
illuminatus-0.0.1.dist-info/RECORD
illuminatus-0.0.1.dist-info/WHEEL
illuminatus-0.0.1.dist-info/metadata.json
illuminatus-0.0.1.dist-info/top_level.txt
