Metadata-Version: 2.0
Name: illuminatus
Version: 0.0.1
Summary: Tools for managing photos and videos
Home-page: http://github.com/lmjohns3/illuminatus/
Author: Leif Johnson
Author-email: leif@lmjohns3.com
License: MIT
Keywords: photo image video media database web
Platform: UNKNOWN
Classifier: Development Status :: 3 - Alpha
Classifier: Environment :: Console
Classifier: License :: OSI Approved :: MIT License
Classifier: Operating System :: OS Independent
Requires: bottle
Requires: climate
Requires: pillow
